README.rst
setup.py
decoratormixins/__init__.py
decoratormixins/auth.py
decoratormixins/cache.py
decoratormixins/clickjacking.py
decoratormixins/conftest.py
decoratormixins/csrf.py
decoratormixins/http.py
decoratormixins/test_mixins.py
django_decoratormixins.egg-info/PKG-INFO
django_decoratormixins.egg-info/SOURCES.txt
django_decoratormixins.egg-info/dependency_links.txt
django_decoratormixins.egg-info/requires.txt
django_decoratormixins.egg-info/top_level.txt