Metadata-Version: 1.1
Name: django-decoratormixins
Version: 1.0.0
Summary: A collection of decorator mixins for Django views.
Home-page: https://github.com/fusionbox/django-decoratormixins
Author: Fusinobox, Inc.
Author-email: programmers@fusionbox.com
License: BSD
Keywords: django decorator mixin class-based-views class based views
Platform: UNKNOWN
Classifier: Development Status :: 4 - Beta
Classifier: Framework :: Django
Classifier: Intended Audience :: Developers
Classifier: License :: OSI Approved :: BSD License
Classifier: Programming Language :: Python
Classifier: Topic :: Software Development :: Libraries
